migrations/__init__.py
auth_system-0.1.dist-info/METADATA
auth_system-0.1.dist-info/WHEEL
auth_system-0.1.dist-info/top_level.txt
auth_system-0.1.dist-info/RECORD
