Metadata-Version: 2.1
Name: auth-system
Version: 0.1
Summary: UNKNOWN
Home-page: UNKNOWN
License: UNKNOWN
Platform: UNKNOWN
Requires-Dist: Django<5.0,>=3.0
Requires-Dist: djangorestframework<4.0,>=3.12
